src/EmailMetadata.py
src/MongoDBHandler.py
src/OutlookConnector.py
src/SQLiteHandler.py
src/__init__.py
src/debug_utils.py
src/mcp_server.py
src/tools/__init__.py
src/tools/embedding_processor.py
mseep_mcp_server_outlook_email-0.1.4.dist-info/METADATA
mseep_mcp_server_outlook_email-0.1.4.dist-info/WHEEL
mseep_mcp_server_outlook_email-0.1.4.dist-info/RECORD
